MANIFEST.in
README.txt
setup.cfg
setup.py
docs/HISTORY.txt
docs/INSTALL.txt
docs/LICENSE.txt
oodt/__init__.py
oodt/filemgr.py
oodt/metadata.py
oodt/oodterrors.py
oodt/profile.py
oodt/query.py
oodt/webgrid.py
oodt/workflow.py
oodt/xmlutils.py
oodt.egg-info/PKG-INFO
oodt.egg-info/SOURCES.txt
oodt.egg-info/dependency_links.txt
oodt.egg-info/entry_points.txt
oodt.egg-info/namespace_packages.txt
oodt.egg-info/top_level.txt
oodt.egg-info/zip-safe
oodt/tests/__init__.py
oodt/tests/profileTest.py
oodt/tests/queryTest.py
oodt/tests/xmlutilsTest.py