Metadata-Version: 1.1
Name: oodt
Version: 1.1
Summary: Apache OODT
Home-page: http://oodt.apache.org/
Author: Sean Kelly
Author-email: kelly@apache.org
License: Apache 2.0
Download-URL: http://pypi.python.org/pypi/oodt/
Keywords: data grid discovery query optimization object middleware archive catalog index
Platform: UNKNOWN
Classifier: Environment :: Console
Classifier: Environment :: No Input/Output (Daemon)
Classifier: Intended Audience :: Developers
Classifier: Intended Audience :: Information Technology
Classifier: Intended Audience :: Science/Research
Classifier: Topic :: Database :: Front-Ends
Classifier: Topic :: Internet :: WWW/HTTP :: Dynamic Content
Classifier: Topic :: Internet :: WWW/HTTP :: HTTP Servers
Classifier: Topic :: Internet :: Z39.50
Classifier: Topic :: Scientific/Engineering
Classifier: Development Status :: 5 - Production/Stable
Classifier: Environment :: Web Environment
Classifier: License :: OSI Approved :: Apache Software License
Classifier: Operating System :: OS Independent
Classifier: Programming Language :: Python
Classifier: Topic :: Internet :: WWW/HTTP
Classifier: Topic :: Software Development :: Libraries :: Python Modules
